{
  "parent": "minecraft:husks/die_to_warden",   
  "criteria": {
    "die_to_wither": {
      "conditions": {
        "entity": [
          {
            "condition": "minecraft:entity_properties",
            "entity": "this",
            "predicate": {
              "minecraft:entity_type": "minecraft:wither"
            }
          }
        ]
      },
      "trigger": "minecraft:entity_killed_player"
    }
  },
  "display": {
    "description": {
      "translate": "Sacrifice yourself to the Wither",
      "color": "red"
    },
    "icon": {
      "id": "minecraft:soul_sand"
    },
    "title": {
      "translate": "Wither Away"
    }
  },
  "requirements": [
    [
      "die_to_wither"
    ]
],
"rewards": {
    "function": "husks:gainsoul"
},
  "sends_telemetry_event": true
}